storpool.spopenstack-3.2.0-py3.8-nspkg.pth
storpool/spopenstack/__init__.py
storpool/spopenstack/spattachdb.py
storpool/spopenstack/splocked.py
storpool.spopenstack-3.2.0.dist-info/METADATA
storpool.spopenstack-3.2.0.dist-info/WHEEL
storpool.spopenstack-3.2.0.dist-info/namespace_packages.txt
storpool.spopenstack-3.2.0.dist-info/top_level.txt
storpool.spopenstack-3.2.0.dist-info/zip-safe
storpool.spopenstack-3.2.0.dist-info/RECORD
